swarmauri_vectorstore_mlm/MlmVectorStore.py
swarmauri_vectorstore_mlm/__init__.py
swarmauri_vectorstore_mlm-0.7.5.dist-info/LICENSE
swarmauri_vectorstore_mlm-0.7.5.dist-info/METADATA
swarmauri_vectorstore_mlm-0.7.5.dist-info/WHEEL
swarmauri_vectorstore_mlm-0.7.5.dist-info/entry_points.txt
swarmauri_vectorstore_mlm-0.7.5.dist-info/RECORD
